paper/__init__.py
paper/tool.py
papersample-0.0.1.dist-info/METADATA
papersample-0.0.1.dist-info/WHEEL
papersample-0.0.1.dist-info/top_level.txt
papersample-0.0.1.dist-info/RECORD
