Metadata-Version: 2.1
Name: papersample
Version: 0.0.1
Summary: 샘플패키지
Home-page: UNKNOWN
Author: UNKNOWN
Author-email: UNKNOWN
License: UNKNOWN
Platform: UNKNOWN
Classifier: Programming Language :: Python :: 3
